README.md
setup.py
minlp_tokenizer.egg-info/PKG-INFO
minlp_tokenizer.egg-info/SOURCES.txt
minlp_tokenizer.egg-info/dependency_links.txt
minlp_tokenizer.egg-info/not-zip-safe
minlp_tokenizer.egg-info/requires.txt
minlp_tokenizer.egg-info/top_level.txt
minlptokenizer/__init__.py
minlptokenizer/config.py
minlptokenizer/exception.py
minlptokenizer/lexicon.py
minlptokenizer/tag.py
minlptokenizer/tokenizer.py
minlptokenizer/vocab.py
minlptokenizer/lexicon/chengyu.txt
minlptokenizer/lexicon/default.txt
minlptokenizer/model/zh/b-coarse-cnn-crf-an2cn.pb
minlptokenizer/model/zh/b-fine-cnn-crf-an2cn.pb
minlptokenizer/vocab/b.14067n.300d.vocab