Metadata-Version: 2.1
Name: minlp-tokenizer
Version: 3.3.1
Summary: MiNLP-Tokenizer中文分词工具
Home-page: https://github.com/XiaoMi/MiNLP
Author: Yuankai Guo, Liang Shi, Yupeng Chen
Author-email: guoyuankai@xiaomi.com, shiliang1@xiaomi.com
License: Apache 2.0
Platform: UNKNOWN
Classifier: License :: OSI Approved :: Apache Software License
Classifier: Programming Language :: Python :: 3
Classifier: Programming Language :: Python :: 3.5
Classifier: Programming Language :: Python :: 3.6
Classifier: Programming Language :: Python :: 3.7
Classifier: Programming Language :: Python :: 3.8
Classifier: Operating System :: OS Independent
Requires-Python: >=3.5, <=3.8
